mattress-0.4.1.dist-info/RECORD
mattress-0.4.1.dist-info/WHEEL
mattress-0.4.1.dist-info/top_level.txt
mattress-0.4.1.dist-info/METADATA
mattress-0.4.1.dist-info/licenses/LICENSE.txt
mattress/InitializedMatrix.py
mattress/initialize.py
mattress/lib_mattress.cpython-313-darwin.so
mattress/__init__.py
mattress/_utils.py
mattress/include/mattress.h
