Metadata-Version: 2.4
Name: mattress
Version: 0.4.1
Summary: All your matrix representations belong here!
Home-page: https://github.com/tatami-inc/mattress
Author: "Jayaram Kancherla, Aaron Lun"
Author-email: jayaram.kancherla@gmail.com
License: MIT
Project-URL: Documentation, https://github.com/tatami-inc/mattress
Platform: any
Classifier: Development Status :: 4 - Beta
Classifier: Programming Language :: Python
Requires-Python: >=3.9
License-File: LICENSE.txt
Requires-Dist: importlib-metadata; python_version < "3.8"
Requires-Dist: numpy>=1.22.4
Requires-Dist: delayedarray>=0.6.2
Requires-Dist: biocutils
Provides-Extra: optional
Requires-Dist: scipy; extra == "optional"
Provides-Extra: testing
Requires-Dist: setuptools; extra == "testing"
Requires-Dist: pytest; extra == "testing"
Requires-Dist: pytest-cov; extra == "testing"
Requires-Dist: scipy; extra == "testing"
Dynamic: license-file
